Workbook
Name aporte: APP_Invest!$D$17
Name patrimonio: APP_Invest!$D$20
Name qtd_anos: APP_Invest!$D$18
Name rendimento_carteira: APP_Invest!$D$13
Name sugestao_investimento: APP_Invest!$D$14
Name taxa_mensal: APP_Invest!$D$19

Sheet APP_Invest
B11: CONFIGURAÇÕES
B12: Salário | D12: 4200
B13: Rendimento Carteira | D13: 0.006
B14: Sugestão de Investimento (30%) | D14: =D12*30% -> 1260
B16: INVESTIMENTO MENSAL
B17: Quanto investir por mês? | D17: 1260
B18: Por quantos anos? | D18: 10
B19: Taxa de rendimento mensal? | D19: 0.01079
B20: Patrimônio Acumulado? | D20: =FV(taxa_mensal,qtd_anos*12,aporte*-1) -> 306538.11
B21: Dividendos Mensais? | D21: =patrimonio*rendimento_carteira -> 1839.2286
B23: CENÁRIOS | D23: Dividendo
A24: 2 | B24: Quanto em 2 Anos? | C24: =FV($D$19,$A24*12,$D$17*-1) -> 34306.81 | D24: =C24*rendimento_carteira -> 205.84086
A25: 5 | B25: Quanto em 5 Anos? | C25: =FV($D$19,$A25*12,$D$17*-1) -> 105558.91 | D25: =C25*rendimento_carteira -> 633.35347
A26: 10 | B26: Quanto em 10 Anos? | C26: =FV($D$19,$A26*12,$D$17*-1) -> 306538.11 | D26: =C26*rendimento_carteira -> 1839.2286
A27: 20 | B27: Quanto em 20 Anos? | C27: =FV($D$19,$A27*12,$D$17*-1) -> 1417750 | D27: =C27*rendimento_carteira -> 8506.4999
A28: 30 | B28: Quanto em 30 Anos? | C28: =FV($D$19,$A28*12,$D$17*-1) -> 5445933.8 | D28: =C28*rendimento_carteira -> 32675.603
B32: PERFIL | C32: Moderado
B33: VALOR A SER INVESTIDO POR MÊS | C33: =aporte -> 1260
B35: TIPO DE FII | C35: Percentual Sugerido | D35: Valores
B36: PAPEL | C36: =VLOOKUP($C$32&"-"&B36,Planilha_Apoio!$B:$E,4,FALSE) -> 0.32 | D36: =C36*$C$33 -> 403.2
B37: TIJOLO | C37: =VLOOKUP($C$32&"-"&B37,Planilha_Apoio!$B:$E,4,FALSE) -> 0.35 | D37: =C37*$C$33 -> 441
B38: HÍBRIDOS | C38: =VLOOKUP($C$32&"-"&B38,Planilha_Apoio!$B:$E,4,FALSE) -> 0.08 | D38: =C38*$C$33 -> 100.8
B39: FOFs | C39: =VLOOKUP($C$32&"-"&B39,Planilha_Apoio!$B:$E,4,FALSE) -> 0.05 | D39: =C39*$C$33 -> 63
B40: DESENVOLVIMENTO | C40: =VLOOKUP($C$32&"-"&B40,Planilha_Apoio!$B:$E,4,FALSE) -> 0.1 | D40: =C40*$C$33 -> 126
B41: HOTELARIAS | C41: =VLOOKUP($C$32&"-"&B41,Planilha_Apoio!$B:$E,4,FALSE) -> 0.1 | D41: =C41*$C$33 -> 126
D42: =SUM(D36:D41) -> 1260

Sheet Planilha_Apoio
B2: CHAVE | C2: PERFIL | D2: TIPO DE FII | E2: %
B3: =C3&"-"&D3 -> Conservador-PAPEL | C3: Conservador | D3: PAPEL | E3: 0.3
B4: =C4&"-"&D4 -> Conservador-TIJOLO | C4: Conservador | D4: TIJOLO | E4: 0.5
B5: =C5&"-"&D5 -> Conservador-HÍBRIDOS | C5: Conservador | D5: HÍBRIDOS | E5: 0.1
B6: =C6&"-"&D6 -> Conservador-FOFs | C6: Conservador | D6: FOFs | E6: 0.1
B7: =C7&"-"&D7 -> Conservador-DESENVOLVIMENTO | C7: Conservador | D7: DESENVOLVIMENTO | E7: 0
B8: =C8&"-"&D8 -> Conservador-HOTELARIAS | C8: Conservador | D8: HOTELARIAS | E8: 0
B9: =C9&"-"&D9 -> Moderado-PAPEL | C9: Moderado | D9: PAPEL | E9: 0.32
B10: =C10&"-"&D10 -> Moderado-TIJOLO | C10: Moderado | D10: TIJOLO | E10: 0.35
B11: =C11&"-"&D11 -> Moderado-HÍBRIDOS | C11: Moderado | D11: HÍBRIDOS | E11: 0.08
B12: =C12&"-"&D12 -> Moderado-FOFs | C12: Moderado | D12: FOFs | E12: 0.05
B13: =C13&"-"&D13 -> Moderado-DESENVOLVIMENTO | C13: Moderado | D13: DESENVOLVIMENTO | E13: 0.1
B14: =C14&"-"&D14 -> Moderado-HOTELARIAS | C14: Moderado | D14: HOTELARIAS | E14: 0.1
... B20: =C20&"-"&D20 -> Agressivo-HOTELARIAS | C20: Agressivo | D20: HOTELARIAS | E20: 0.1
